streamdaq/CompactData.py
streamdaq/CustomReducers.py
streamdaq/DaQMeasures.py
streamdaq/SchemaValidator.py
streamdaq/StreamDaQ.py
streamdaq/Task.py
streamdaq/Windows.py
streamdaq/__init__.py
streamdaq/artificial_stream_generators.py
streamdaq/main.py
streamdaq/utils.py
streamdaq-0.4.0.dist-info/licenses/LICENSE
streamdaq-0.4.0.dist-info/METADATA
streamdaq-0.4.0.dist-info/WHEEL
streamdaq-0.4.0.dist-info/top_level.txt
streamdaq-0.4.0.dist-info/RECORD
