Metadata-Version: 2.4
Name: streamdaq
Version: 0.4.0
Summary: Plug-and-play real-time quality monitoring for data streams!
Author: George Atmatzidis, Apostolos Giannoulidis
Author-email: Vassilis Papastergios <papster@csd.auth.gr>, Anastasios Gounaris <gounaria@csd.auth.gr>
Maintainer: George Atmatzidis
Maintainer-email: Vassilis Papastergios <papster@csd.auth.gr>
License: MIT
Project-URL: Homepage, https://bilpapster.github.io/stream-DaQ/
Project-URL: Documentation, https://bilpapster.github.io/stream-DaQ/
Project-URL: Repository, https://github.com/Bilpapster/stream-DaQ
Project-URL: Bug Tracker, https://github.com/Bilpapster/stream-DaQ/issues
Keywords: data-quality,streaming,real-time,monitoring,data-engineering
Classifier: Programming Language :: Python :: 3
Classifier: Programming Language :: Python :: 3.11
Classifier: Programming Language :: Python :: 3.12
Classifier: License :: OSI Approved :: MIT License
Classifier: Operating System :: OS Independent
Classifier: Development Status :: 4 - Beta
Classifier: Intended Audience :: Developers
Classifier: Intended Audience :: Science/Research
Classifier: Topic :: Software Development :: Libraries :: Python Modules
Classifier: Topic :: Scientific/Engineering :: Information Analysis
Requires-Python: >=3.11
License-File: LICENSE
Requires-Dist: pathway==0.21.*
Requires-Dist: matplotlib==3.10.1
Requires-Dist: python-dateutil==2.9.0.post0
Requires-Dist: datasketch~=1.6.5
Requires-Dist: datasketches~=5.1.0
Provides-Extra: dev
Requires-Dist: pytest>=7.0; extra == "dev"
Requires-Dist: pytest-cov>=4.0; extra == "dev"
Requires-Dist: black>=22.0; extra == "dev"
Requires-Dist: isort>=5.10; extra == "dev"
Requires-Dist: flake8>=5.0; extra == "dev"
Requires-Dist: mypy>=1.0; extra == "dev"
Requires-Dist: pre-commit>=2.20; extra == "dev"
Provides-Extra: docs
Requires-Dist: sphinx>=8.2.3; extra == "docs"
Requires-Dist: sphinx-design>=0.6.1; extra == "docs"
Requires-Dist: sphinx-book-theme>=1.1.4; extra == "docs"
Requires-Dist: sphinx-rtd-theme>=3.0.2; extra == "docs"
Requires-Dist: sphinxawesome-theme>=5.3.2; extra == "docs"
Dynamic: license-file
